indexforge/__init__.py
indexforge/ai/__init__.py
indexforge/ai/llm_index_creator.py
indexforge/core/__init__.py
indexforge/core/constituent.py
indexforge/core/index.py
indexforge/core/types.py
indexforge/core/universe.py
indexforge/data/__init__.py
indexforge/data/connectors/__init__.py
indexforge/data/connectors/base.py
indexforge/data/connectors/openbb.py
indexforge/data/connectors/yahoo.py
indexforge/data/provider.py
indexforge/rebalancing/__init__.py
indexforge/rebalancing/schedule.py
indexforge/selection/__init__.py
indexforge/selection/composite.py
indexforge/selection/criteria.py
indexforge/selection/theme.py
indexforge/validation/__init__.py
indexforge/validation/report.py
indexforge/validation/rules.py
indexforge/weighting/__init__.py
indexforge/weighting/methods.py
indexforge-0.1.5.dist-info/METADATA
indexforge-0.1.5.dist-info/WHEEL
indexforge-0.1.5.dist-info/licenses/LICENSE
indexforge-0.1.5.dist-info/RECORD
