Metadata-Version: 2.4
Name: indexforge
Version: 0.1.5
Summary: A domain-driven Python module for creating and managing financial indices
License: AGPL-3.0-or-later
License-File: LICENSE
Keywords: finance,index,stock market,investment,portfolio,benchmark,weighting,rebalancing
Author: Reuben Capio
Author-email: reuben@indexmaker.io
Requires-Python: >=3.10,<3.13
Classifier: Development Status :: 3 - Alpha
Classifier: Intended Audience :: Developers
Classifier: Intended Audience :: Financial and Insurance Industry
Classifier: License :: OSI Approved :: GNU Affero General Public License v3 or later (AGPLv3+)
Classifier: License :: OSI Approved :: MIT License
Classifier: Operating System :: OS Independent
Classifier: Programming Language :: Python :: 3
Classifier: Programming Language :: Python :: 3.10
Classifier: Programming Language :: Python :: 3.11
Classifier: Programming Language :: Python :: 3.12
Classifier: Programming Language :: Python :: 3.9
Classifier: Topic :: Office/Business :: Financial :: Investment
Classifier: Typing :: Typed
Provides-Extra: ai
Provides-Extra: all
Requires-Dist: alembic (>=1.13.1,<2.0.0)
Requires-Dist: asgiref (>=3.7.0,<4.0.0)
Requires-Dist: asyncpg (>=0.29.0,<0.30.0)
Requires-Dist: bcrypt (>=4.1.2,<5.0.0)
Requires-Dist: celery[redis] (>=5.3.6,<6.0.0)
Requires-Dist: email-validator (>=2.3.0,<3.0.0)
Requires-Dist: fastapi (>=0.128.0,<0.129.0)
Requires-Dist: httpx (>=0.26.0,<0.27.0)
Requires-Dist: numpy (>=1.24.0,<2.0.0)
Requires-Dist: openai (>=1.0.0,<2.0.0) ; extra == "ai" or extra == "all"
Requires-Dist: openbb (>=4.5.0,<5.0.0)
Requires-Dist: pandas (>=2.0.0,<3.0.0)
Requires-Dist: passlib[bcrypt] (>=1.7.4,<2.0.0)
Requires-Dist: psycopg2-binary (>=2.9.9,<3.0.0)
Requires-Dist: pydantic-settings (>=2.1.0,<3.0.0)
Requires-Dist: python-jose[cryptography] (>=3.3.0,<4.0.0)
Requires-Dist: python-multipart (==0.0.20)
Requires-Dist: redis (>=5.0.1,<6.0.0)
Requires-Dist: sqlalchemy (>=2.0.25,<3.0.0)
Requires-Dist: supervisor (>=4.3.0,<5.0.0)
Requires-Dist: uvicorn[standard] (>=0.40.0,<0.41.0)
Requires-Dist: yfinance (>=0.2.0,<0.3.0)
Project-URL: Homepage, https://github.com/reubencapio/indexmaker
Project-URL: Repository, https://github.com/reubencapio/indexmaker
